Workbook

Sheet README
A1: Insperity Project Portfolio — Holonic Semantic Governance Program
A2: Prepared by Jeffrey Wallk, The Value Enablement Group, LLC · illustrative planning portfolio, not an Insperity-endorsed document
A4: How this list was derived
A5: Roadmap: Insperity Intelligence Holarchy (IIH) four-phase plan — Phase 0 Foundation (M1–2), Phase 1 Jarvis MVP (M3–6), Phase 2 Expansion (M7–12), Phase 3 Enterprise Holarchy (M13–18).
A6: Value proposition: nine capabilities (C1–C9) from 'The Value Jeffrey Brings to Insperity' and the IIH trust model; every project realizes at least one.
A7: Policies & governance: all 142 rules in the SSOT HR Policy Rules Register are assigned to at least one owning project (see Rule Traceability).
A9: Sheets
A10: Projects — one row per project: phase, owner, capabilities, deliverables, KPI, dependencies, rule coverage.
A11: Rule Traceability — one row per project × rule, with statute, domain, type and lifecycle phase from the register.
A12: Coverage — live formulas: projects and rules by phase, domain and capability.
A13: Phase Gates — governance gate criteria each phase must clear before the next is funded.
A15: Companion files
A16: Insperity Solution Architecture.html · Insperity PLM Dashboard.html · Insperity Impact Tracer.html

Sheet Projects
A1: Project ID | B1: Project | C1: Phase | D1: Window | E1: Domain holon | F1: Owner | G1: Priority | H1: Size | I1: Current lifecycle stage | J1: Value-prop capabilities | K1: Summary | L1: Key deliverables | M1: Success KPI | N1: Depends on | O1: Rules owned | P1: Rule IDs | Q1: Governing regimes
A2: ISP-01 | B2: Core PEO Ontology (isp-core) & ORSD Templates | C2: Phase 0 · Foundation | D2: Months 1–2 | E2: Enterprise L4 / isp-core | F2: Knowledge Engineer | G2: Critical | H2: M | I2: Deliver | J2: C1 Single source of truth for policy; C7 Governance that scales | K2: Canonical entity model (ClientCompany, Worker, Jurisdiction, EmploymentType, StatutoryStandard) and the owl:imports federation contract every domain holon inherits. | L2: isp-core OWL + SKOS vocabularies; ORSD templates for 6 IP asset types; federation pattern for 5 domain ontologies | M2: Core ontology live; ORSD templates approved | N2: — | O2: =COUNTIF('Rule Traceability'!$A:$A,A2) -> 4 | P2: GOV-004, GOV-005, GOV-017, GOV-018 | Q2: ISO 8000; OMG ODM/DPROD; LKIF
A3: ISP-02 | B3: SSOT Policy Rules Register & LKIF Wave 1 | C3: Phase 0 · Foundation | D3: Months 1–2 | E3: All L2 domain holons | F3: Compliance Governance Lead | G3: Critical | H3: M | I3: Deliver | J3: C1 Single source of truth for policy; C5 Faster, auditable compliance response | K3: Turns the 142-rule register into governed LKIF obligations, permissions and prohibitions paired with SHACL shapes — the seed library for compilation. | L3: 142 rules keyed and owned; LKIF norms for 4 federal frameworks; rule-to-statute provenance | M3: LKIF library covers 4 frameworks; 100% rules with owner + source | N3: ISP-01 | O3: =COUNTIF('Rule Traceability'!$A:$A,A3) -> 8 | P3: PAY-001, PAY-002, PAY-008, BEN-005, CMP-001, TAL-001, GOV-017, GOV-023 | Q3: FLSA; Title VII / EEOC; OSHA; ERISA
A4: ISP-03 | B4: Box AI Admission Bridge (33M records → L1 holons) | C4: Phase 0 · Foundation | D4: Months 1–2 | E4: Mediation Holon | F4: Platform Team Lead | G4: High | H4: M | I4: Develop | J4: C1 Single source of truth for policy; C8 Trusted HR assistant (Jarvis, MTBH-governed) | K4: Connects the existing Box AI content cloud to the admission pipeline so plan documents, handbooks and carrier contracts become SHACL-validated knowledge holons. | L4: Admission connector; SHACL admission gate; quarantine + KGCL rejection records | M4: ≥2,000 seed assets admitted; SHACL pass ≥98% | N4: ISP-01 | O4: =COUNTIF('Rule Traceability'!$A:$A,A4) -> 2 | P4: GOV-006, GOV-010 | Q4: SOC 2; HIPAA Security Rule
A5: ISP-04 | B5: SAML Identity & URI Resolution Registry v1 | C5: Phase 0 · Foundation | D5: Months 1–2 | E5: Mediation Holon | F5: Identity Architect | G5: Critical | H5: S | I5: Develop | J5: C9 Co-employment tenant isolation; C7 Governance that scales | K5: Canonical Worksite Employee and Client Employer entity IDs, resolving payroll, carrier, 401(k), ATS and LMS identifiers before any domain needs them. | L5: Entity ID schemas; resolution service; ISO 8000 uniqueness checks | M5: Canonical IDs for employee & employer; 0 unresolved duplicates in pilot | N5: ISP-01 | O5: =COUNTIF('Rule Traceability'!$A:$A,A5) -> 2 | P5: GOV-007, TEC-001 | Q5: SOC 2; CCPA/CPRA; ISO 8000
A6: ISP-05 | B6: KGCL Change Governance & Semantic Governance Council Charter | C6: Phase 0 · Foundation | D6: Months 1–2 | E6: Enterprise L4 | F6: Governance Lead | G6: High | H6: S | I6: Deliver | J6: C7 Governance that scales; C5 Faster, auditable compliance response | K6: Five-dimension (WHO/WHAT/WHEN/WHERE/WHY) change records on every triple; DEV/STG/PRD promotion gates; ARB routing for ontology change. | L6: Council charter; KGCL capture live; promotion-gate workflow; MTBH before-state benchmark | M6: 100% ontology changes carry KGCL record | N6: ISP-01 | O6: =COUNTIF('Rule Traceability'!$A:$A,A6) -> 3 | P6: GOV-002, GOV-003, GOV-018 | Q6: ISO/IEC 42001; NIST AI RMF
A7: ISP-06 | B7: Payroll & Tax Domain Holon (isp-pay) | C7: Phase 1 · Jarvis MVP | D7: Months 3–6 | E7: L2 · Payroll & Tax | F7: Domain Team — Payroll | G7: Critical | H7: L | I7: Design | J7: C1 Single source of truth for policy; C5 Faster, auditable compliance response; C8 Trusted HR assistant (Jarvis, MTBH-governed) | K7: FLSA and state overtime, multi-state wage bases, SUTA/SIT nexus and PFML withholding modeled once and compiled to runtime checks for gross-to-net. | L7: isp-pay ontology; SHACL/SWRL invariants; domain agent; hybrid vector DB; 6 PEPs | M7: Pre-run catch rate ≥99%; manual correction hours −80% | N7: ISP-01, ISP-02, ISP-08 | O7: =COUNTIF('Rule Traceability'!$A:$A,A7) -> 21 | P7: PAY-002, PAY-005, PAY-006, PAY-007, PAY-010, PAY-011, PAY-012, PAY-013, PAY-014, PAY-017, PAY-018, PAY-021, PAY-025, PAY-026, PAY-027, CMP-018, PAY-009, PAY-015, PAY-016, PAY-019, PAY-020 | Q7: FLSA; State wage & hour codes; SUTA / SIT / local tax; State PFML
A8: ISP-07 | B8: Benefits & Retirement Domain Holon (isp-ben) | C8: Phase 1 · Jarvis MVP | D8: Months 3–6 | E8: L2 · Benefits | F8: Domain Team — Benefits | G8: Critical | H8: L | I8: Design | J8: C1 Single source of truth for policy; C8 Trusted HR assistant (Jarvis, MTBH-governed); C2 Personal-model-driven compliance | K8: Reference implementation of the five-component holon: MEP/PEP fiduciary structure, ACA ALE and affordability logic, SECURE 2.0 eligibility and COBRA events. | L8: isp-ben ontology; ERISA/ACA-grounded PEPs; carrier EDI 834 alignment; GraphRAG index | M8: Benefits answer accuracy ≥98%; stale-answer risk −90% | N8: ISP-01, ISP-02, ISP-03 | O8: =COUNTIF('Rule Traceability'!$A:$A,A8) -> 21 | P8: BEN-001, BEN-002, BEN-003, BEN-004, BEN-005, BEN-006, BEN-008, BEN-009, BEN-010, BEN-012, BEN-014, BEN-015, BEN-016, BEN-019, BEN-022, BEN-007, BEN-011, BEN-013, BEN-017, BEN-018, BEN-020 | Q8: ERISA; ACA; SECURE 2.0; CAA / TiC / MHPAEA; COBRA; HIPAA
A9: ISP-08 | B9: SHACL-to-Policy Compilation Pipeline | C9: Phase 1 · Jarvis MVP | D9: Months 3–6 | E9: Mediation Holon | F9: Gateway Engineering Lead | G9: Critical | H9: M | I9: Design | J9: C1 Single source of truth for policy; C7 Governance that scales | K9: Six stages — parse, extract, harmonize, target-map, generate, KGCL publish — emitting dbt/SQL tests and OPA/Rego policies with URI traceability to the source norm. | L9: Rule projection agents; compiled policy registry; dbt + Rego emitters | M9: Law change → compiled policy in production ≤5 days; 100% runtime rules carry source URI | N9: ISP-01, ISP-02 | O9: =COUNTIF('Rule Traceability'!$A:$A,A9) -> 6 | P9: GOV-001, GOV-019, GOV-020, GOV-022, GOV-024, TEC-021 | Q9: SOC 1 (SSAE 18); SOC 2
A10: ISP-09 | B10: Rule Harmonization Engine (most-stringent-rule) | C10: Phase 1 · Jarvis MVP | D10: Months 3–6 | E10: Mediation Holon | F10: Knowledge Engineer | G10: High | H10: S | I10: Define | J10: C1 Single source of truth for policy; C5 Faster, auditable compliance response | K10: SPARQL conflict scans across federal/state/local norms, enforcing highest-employee-protection precedence before any rule is published. | L10: Conflict scan library; precedence model; conflict review queue | M10: 0 unresolved jurisdiction conflicts at publish | N10: ISP-02 | O10: =COUNTIF('Rule Traceability'!$A:$A,A10) -> 5 | P10: GOV-008, GOV-009, PAY-002, PAY-004, PAY-026 | Q10: FLSA; State wage & hour codes; Municipal minimum wage
A11: ISP-10 | B11: RDSG Gateway, MTBH Circuit Breaker & Simplex Action Gate | C11: Phase 1 · Jarvis MVP | D11: Months 3–6 | E11: L3 · Gateway Holon | F11: Gateway Engineering Lead | G11: Critical | H11: L | I11: Design | J11: C8 Trusted HR assistant (Jarvis, MTBH-governed); C9 Co-employment tenant isolation; C5 Faster, auditable compliance response | K11: Seven-stage traversal: 5D Requirement Context Bundle, PEP evaluation, STPA unsafe-control-action checks, compiled directives, and human sign-off on every irreversible action. | L11: RCB assembler; PEP engine; MTBH 5D scoring; Simplex gate; sanitization queue | M11: Trip rate ≤2%; 100% irreversible actions human-gated | N11: ISP-08, ISP-04 | O11: =COUNTIF('Rule Traceability'!$A:$A,A11) -> 9 | P11: GOV-011, GOV-012, GOV-013, GOV-014, GOV-015, GOV-016, GOV-021, PAY-028, PAY-029 | Q11: NIST AI RMF; ISO/IEC 42001; STPA/STAMP
A12: ISP-11 | B12: Multi-Tenant Isolation & PHI Policy Enforcement Points | C12: Phase 1 · Jarvis MVP | D12: Months 3–6 | E12: L2 · HR Technology | F12: Security Architect | G12: Critical | H12: M | I12: Design | J12: C9 Co-employment tenant isolation | K12: Tenant boundaries enforced at every data layer and compiled OPA rules for PHI access (role + tenant + MFA), so no client's data ever resolves in another's answer. | L12: Isolation model; compiled RBAC/ABAC policies; immutable audit log | M12: MTBH_WHERE ≥99.5%; 0 cross-tenant incidents | N12: ISP-04, ISP-08 | O12: =COUNTIF('Rule Traceability'!$A:$A,A12) -> 8 | P12: TEC-001, TEC-004, TEC-005, TEC-007, TEC-008, TEC-013, TEC-021, BEN-016 | Q12: HIPAA Security Rule; SOC 2; CCPA/CPRA
A13: ISP-12 | B13: Employee Jarvis & Machine APIs (pilot, 3–5 clients) | C13: Phase 1 · Jarvis MVP | D13: Months 3–6 | E13: Knowledge services | F13: Product & AI Science | G13: High | H13: L | I13: Define | J13: C8 Trusted HR assistant (Jarvis, MTBH-governed); C2 Personal-model-driven compliance | K13: Self-service answers on PTO, eligibility, open enrollment and pay stubs — every answer trust-scored and traced to the plan clause or statute behind it. | L13: Conversational UI; REST/GraphQL + MCP APIs; provenance display; MTBH dashboard | M13: Self-service deflection ≥40%; P95 ≤3s | N13: ISP-06, ISP-07, ISP-10 | O13: =COUNTIF('Rule Traceability'!$A:$A,A13) -> 5 | P13: GOV-014, GOV-021, GOV-022, BEN-021, BEN-022 | Q13: NIST AI RMF; ERISA disclosure rules; State privacy acts
... A29: ISP-28 | B29: 50-State Digital Orchestration Rollout | C29: Phase 3 · Enterprise Holarchy | D29: Months 13–18 | E29: Program Office | F29: Program Office | G29: High | H29: L | I29: Discover | J29: C7 Governance that scales; C8 Trusted HR assistant (Jarvis, MTBH-governed) | K29: Full rollout across the expanded client base with carriers, 401(k), ATS and LMS federated through the identity registry. | L29: State-by-state activation plan; ecosystem federation; hypercare | M29: 50 states governed; full client base on the holarchy | N29: ISP-13, ISP-15, ISP-22 | O29: =COUNTIF('Rule Traceability'!$A:$A,A29) -> 4 | P29: PAY-013, PAY-014, CMP-017, PEO-007 | Q29: All state regimes

Sheet Rule Traceability
A1: Project ID | B1: Project | C1: Phase | D1: Rule ID | E1: Domain | F1: Sub-category | G1: Rule | H1: Rule type | I1: Statute / standard | J1: Jurisdiction | K1: Lifecycle phase | L1: Owning holon
A2: ISP-01 | B2: Core PEO Ontology (isp-core) & ORSD Templates | C2: Phase 0 · Foundation | D2: GOV-004 | E2: Governance & Architecture | F2: Core Ontology | G2: Core Entity Model Definition | H2: Structural Invariant | I2: Root Core PEO Ontology (isp-core) | J2: N/A | K2: Design-Time | L2: Enterprise (L4) / isp-core
A3: ISP-01 | B3: Core PEO Ontology (isp-core) & ORSD Templates | C3: Phase 0 · Foundation | D3: GOV-005 | E3: Governance & Architecture | F3: Ontology Federation | G3: Domain Ontology Federation via owl:imports | H3: Structural Invariant | I3: Federated ontology standard | J3: N/A | K3: Design-Time | L3: L2 Domain Holons
A4: ISP-01 | B4: Core PEO Ontology (isp-core) & ORSD Templates | C4: Phase 0 · Foundation | D4: GOV-017 | E4: Governance & Architecture | F4: Rule Representation | G4: LKIF Deontic Norm + SHACL Shape Dual Representation | H4: Structural Invariant | I4: LKIF Core / W3C SHACL | J4: N/A | K4: Design-Time | L4: L2 Domain Holons (L1 Knowledge Holons)
A5: ISP-01 | B5: Core PEO Ontology (isp-core) & ORSD Templates | C5: Phase 0 · Foundation | D5: GOV-018 | E5: Governance & Architecture | F5: Provenance | G5: Provenance & Change Management - ORSD + KGCL Metadata | H5: Structural Invariant | I5: Ontology Requirements Specification Document (ORSD) / Knowledge Graph Change Language (KGCL) | J5: N/A | K5: Design-Time | L5: Enterprise (L4) / L2 Domain Holons
A6: ISP-02 | B6: SSOT Policy Rules Register & LKIF Wave 1 | C6: Phase 0 · Foundation | D6: PAY-001 | E6: Payroll & Tax | F6: Wage & Hour | G6: Federal FLSA Exemption Salary Threshold & Duties Test | H6: Threshold | I6: FLSA (federal) | J6: Federal | K6: Run | L6: Payroll & Tax Domain Holon (isp-pay)
A7: ISP-02 | B7: SSOT Policy Rules Register & LKIF Wave 1 | C7: Phase 0 · Foundation | D7: PAY-002 | E7: Payroll & Tax | F7: Wage & Hour | G7: State Exemption Salary Thresholds Override Federal | H7: Obligation | I7: State labor codes (e.g., CA, NY, WA) | J7: State (CA, NY, WA, others) | K7: Run | L7: Payroll & Tax Domain Holon
A8: ISP-02 | B8: SSOT Policy Rules Register & LKIF Wave 1 | C8: Phase 0 · Foundation | D8: PAY-008 | E8: Payroll & Tax | F8: Overtime | G8: Federal Weekly Overtime (FLSA 40-hour rule) | H8: Obligation | I8: FLSA (federal) | J8: Federal | K8: Run | L8: Payroll & Tax Domain Holon
A9: ISP-02 | B9: SSOT Policy Rules Register & LKIF Wave 1 | C9: Phase 0 · Foundation | D9: BEN-005 | E9: Benefits | F9: ERISA Fiduciary | G9: Master Plan Document / MEP-PEP Fiduciary Structure | H9: Structural Invariant | I9: ERISA | J9: Federal | K9: Define | L9: Benefits Domain Holon
A10: ISP-02 | B10: SSOT Policy Rules Register & LKIF Wave 1 | C10: Phase 0 · Foundation | D10: CMP-001 | E10: Compliance & Risk | F10: OSHA Recordkeeping | G10: OSHA Form 300/300A/301 Electronic Submission | H10: Reporting Deadline | I10: OSHA Injury Tracking Application (ITA) | J10: Federal (+ State Plans) | K10: Run | L10: Compliance & Risk Domain Holon (isp-comp)
A11: ISP-02 | B11: SSOT Policy Rules Register & LKIF Wave 1 | C11: Phase 0 · Foundation | D11: TAL-001 | E11: Talent Management | F11: Anti-Discrimination | G11: Title VII / ADEA / GINA Hiring Screen | H11: Prohibition | I11: Title VII, ADEA, GINA (federal) | J11: Federal | K11: Discover | L11: Talent Domain Holon (isp-tal)
A12: ISP-02 | B12: SSOT Policy Rules Register & LKIF Wave 1 | C12: Phase 0 · Foundation | D12: GOV-017 | E12: Governance & Architecture | F12: Rule Representation | G12: LKIF Deontic Norm + SHACL Shape Dual Representation | H12: Structural Invariant | I12: LKIF Core / W3C SHACL | J12: N/A | K12: Design-Time | L12: L2 Domain Holons (L1 Knowledge Holons)
... A193: ISP-28 | B193: 50-State Digital Orchestration Rollout | C193: Phase 3 · Enterprise Holarchy | D193: PEO-007 | E193: PEO Operational Standards | F193: State Licensing | G193: State PEO Licensing Board Registration Compliance | H193: Obligation | I193: State PEO licensing statutes | J193: State (varies) | K193: Run | L193: Enterprise (L4)

Sheet Coverage
A1: Portfolio coverage (live formulas)
A3: Phase | B3: Projects | C3: Critical projects | D3: Rule assignments
A4: Phase 0 · Foundation | B4: =COUNTIF(Projects!$C:$C,A4) -> 5 | C4: =COUNTIFS(Projects!$C:$C,A4,Projects!$G:$G,"Critical") -> 3 | D4: =COUNTIF('Rule Traceability'!$C:$C,A4) -> 19
A5: Phase 1 · Jarvis MVP | B5: =COUNTIF(Projects!$C:$C,A5) -> 7 | C5: =COUNTIFS(Projects!$C:$C,A5,Projects!$G:$G,"Critical") -> 5 | D5: =COUNTIF('Rule Traceability'!$C:$C,A5) -> 75
A6: Phase 2 · Expansion | B6: =COUNTIF(Projects!$C:$C,A6) -> 9 | C6: =COUNTIFS(Projects!$C:$C,A6,Projects!$G:$G,"Critical") -> 1 | D6: =COUNTIF('Rule Traceability'!$C:$C,A6) -> 68
A7: Phase 3 · Enterprise Holarchy | B7: =COUNTIF(Projects!$C:$C,A7) -> 7 | C7: =COUNTIFS(Projects!$C:$C,A7,Projects!$G:$G,"Critical") -> 0 | D7: =COUNTIF('Rule Traceability'!$C:$C,A7) -> 30
A8: Total | B8: =SUM(B4:B7) -> 28 | C8: =SUM(C4:C7) -> 9 | D8: =SUM(D4:D7) -> 192
A11: Register domain | B11: Rules in register | C11: Project assignments | D11: Rules uncovered
A12: Payroll & Tax | B12: =COUNTIF(Register!$B:$B,A12) -> 29 | C12: =COUNTIF('Rule Traceability'!$E:$E,A12) -> 35 | D12: =COUNTIFS(Register!$B:$B,A12,Register!$D:$D,0) -> 0
A13: Benefits | B13: =COUNTIF(Register!$B:$B,A13) -> 22 | C13: =COUNTIF('Rule Traceability'!$E:$E,A13) -> 25 | D13: =COUNTIFS(Register!$B:$B,A13,Register!$D:$D,0) -> 0
A14: Compliance & Risk | B14: =COUNTIF(Register!$B:$B,A14) -> 22 | C14: =COUNTIF('Rule Traceability'!$E:$E,A14) -> 26 | D14: =COUNTIFS(Register!$B:$B,A14,Register!$D:$D,0) -> 0
A15: Talent Management | B15: =COUNTIF(Register!$B:$B,A15) -> 17 | C15: =COUNTIF('Rule Traceability'!$E:$E,A15) -> 21 | D15: =COUNTIFS(Register!$B:$B,A15,Register!$D:$D,0) -> 0
A16: HR Technology | B16: =COUNTIF(Register!$B:$B,A16) -> 21 | C16: =COUNTIF('Rule Traceability'!$E:$E,A16) -> 33 | D16: =COUNTIFS(Register!$B:$B,A16,Register!$D:$D,0) -> 0
A17: PEO Operational Standards | B17: =COUNTIF(Register!$B:$B,A17) -> 7 | C17: =COUNTIF('Rule Traceability'!$E:$E,A17) -> 9 | D17: =COUNTIFS(Register!$B:$B,A17,Register!$D:$D,0) -> 0
A18: Governance & Architecture | B18: =COUNTIF(Register!$B:$B,A18) -> 24 | C18: =COUNTIF('Rule Traceability'!$E:$E,A18) -> 43 | D18: =COUNTIFS(Register!$B:$B,A18,Register!$D:$D,0) -> 0
A19: Total | B19: =SUM(B12:B18) -> 142 | C19: =SUM(C12:C18) -> 192 | D19: =SUM(D12:D18) -> 0
A22: Value-prop capability | B22: Projects realizing it
A23: C1 Single source of truth for policy | B23: =COUNTIF(Projects!$J:$J,"*"&A23&"*") -> 14
A24: C2 Personal-model-driven compliance | B24: =COUNTIF(Projects!$J:$J,"*"&A24&"*") -> 5
A25: C3 On-demand compliance training | B25: =COUNTIF(Projects!$J:$J,"*"&A25&"*") -> 1
A26: C4 Continuous values measurement | B26: =COUNTIF(Projects!$J:$J,"*"&A26&"*") -> 3
A27: C5 Faster, auditable compliance response | B27: =COUNTIF(Projects!$J:$J,"*"&A27&"*") -> 12
A28: C6 Analytics you can trust | B28: =COUNTIF(Projects!$J:$J,"*"&A28&"*") -> 5
A29: C7 Governance that scales | B29: =COUNTIF(Projects!$J:$J,"*"&A29&"*") -> 9
A30: C8 Trusted HR assistant (Jarvis, MTBH-governed) | B30: =COUNTIF(Projects!$J:$J,"*"&A30&"*") -> 9
A31: C9 Co-employment tenant isolation | B31: =COUNTIF(Projects!$J:$J,"*"&A31&"*") -> 5

Sheet Register
A1: Rule_ID | B1: Domain | C1: Rule_Name | D1: Assignments
A2: PAY-001 | B2: Payroll & Tax | C2: Federal FLSA Exemption Salary Threshold & Duties Test | D2: =COUNTIF('Rule Traceability'!$D:$D,A2) -> 1
A3: PAY-002 | B3: Payroll & Tax | C3: State Exemption Salary Thresholds Override Federal | D3: =COUNTIF('Rule Traceability'!$D:$D,A3) -> 3
A4: PAY-003 | B4: Payroll & Tax | C4: DOL Multi-Factor Economic Reality Test | D4: =COUNTIF('Rule Traceability'!$D:$D,A4) -> 1
A5: PAY-004 | B5: Payroll & Tax | C5: State 'ABC' Test for Contractor Status | D5: =COUNTIF('Rule Traceability'!$D:$D,A5) -> 2
A6: PAY-005 | B6: Payroll & Tax | C6: California Daily Overtime - Tier 1 | D6: =COUNTIF('Rule Traceability'!$D:$D,A6) -> 1
A7: PAY-006 | B7: Payroll & Tax | C7: California Daily Overtime - Tier 2 (Double-Time) | D7: =COUNTIF('Rule Traceability'!$D:$D,A7) -> 1
A8: PAY-007 | B8: Payroll & Tax | C8: Alaska & Nevada Daily/24-Hour Overtime Rules | D8: =COUNTIF('Rule Traceability'!$D:$D,A8) -> 1
A9: PAY-008 | B9: Payroll & Tax | C9: Federal Weekly Overtime (FLSA 40-hour rule) | D9: =COUNTIF('Rule Traceability'!$D:$D,A9) -> 1
A10: PAY-009 | B10: Payroll & Tax | C10: Predictive Scheduling / Fair Workweek Laws | D10: =COUNTIF('Rule Traceability'!$D:$D,A10) -> 1
A11: PAY-010 | B11: Payroll & Tax | C11: Meal & Rest Period Penalty Pay | D11: =COUNTIF('Rule Traceability'!$D:$D,A11) -> 1
A12: PAY-011 | B12: Payroll & Tax | C12: Multi-State Wage Base & Reciprocal Tax Agreement Logic | D12: =COUNTIF('Rule Traceability'!$D:$D,A12) -> 1
A13: PAY-012 | B13: Payroll & Tax | C13: SUTA Experience Rating Transfer / Allocation | D13: =COUNTIF('Rule Traceability'!$D:$D,A13) -> 1
... A143: GOV-024 | B143: Governance & Architecture | C143: Zero Graph Latency Runtime Principle | D143: =COUNTIF('Rule Traceability'!$D:$D,A143) -> 1

Sheet Phase Gates
A1: Phase | B1: Window | C1: Gate criteria
A2: Phase 0 · Foundation | B2: Months 1–2 | C2: Gate 0 — ≥2,000 seed IP assets admitted with SHACL validation ≥98%; LKIF library covering FLSA, EEOC, OSHA, ERISA approved; ORSD templates approved for all six IP asset types.
A3: Phase 1 · Jarvis MVP | B3: Months 3–6 | C3: Gate 1 — MTBH_WHERE ≥99.5%, MTBH_WHAT ≥97%, P95 ≤3s, circuit-breaker trip rate ≤2%, self-service deflection ≥40%, zero cross-tenant incidents.
A4: Phase 2 · Expansion | B4: Months 7–12 | C4: Gate 2 — all six domain holons in production, MTBH aggregate ≥96% every dimension, 25–40 client companies, zero unflagged compliance obligations at go-live.
A5: Phase 3 · Enterprise Holarchy | B5: Months 13–18 | C5: Gate 3 — MTBH aggregate ≥97% sustained, zero cumulative cross-tenant breaches, data product live, full 50-state rollout complete.
